csdatatools/__init__.py
csdatatools/__main__.py
csdatatools/datasets/__init__.py
csdatatools/datasets/cincensus/__init__.py
csdatatools/datasets/cincensus/cin_record.py
csdatatools/datasets/cincensus/cli.py
csdatatools/datasets/cincensus/config.py
csdatatools/datasets/cincensus/converters.py
csdatatools/datasets/cincensus/filters.py
csdatatools/datasets/cincensus/validator.py
csdatatools/spec/__init__.py
csdatatools/spec/cin/__init__.py
csdatatools/spec/cin/cin-2022.xsd
csdatatools/spec/cin/cin-2022.yaml
csdatatools/spec/cin/samples/cin-2022.xml
csdatatools/stream/__init__.py
csdatatools/stream/tablib.py
csdatatools-0.1.0a3.dist-info/LICENSE
csdatatools-0.1.0a3.dist-info/WHEEL
csdatatools-0.1.0a3.dist-info/METADATA
csdatatools-0.1.0a3.dist-info/RECORD
