Metadata-Version: 2.1
Name: csdatatools
Version: 0.1.0a3
Summary: Children's Services Data Tools - Utilities for cleaning and normalising CS data by Social Finance
License: MIT
Author: Michael Hanks
Author-email: michael.hanks@socialfinance.org.uk
Requires-Python: >=3.8,<4.0
Classifier: License :: OSI Approved :: MIT License
Classifier: Programming Language :: Python :: 3
Classifier: Programming Language :: Python :: 3.10
Classifier: Programming Language :: Python :: 3.8
Classifier: Programming Language :: Python :: 3.9
Requires-Dist: PyYAML (>=6.0,<7.0)
Requires-Dist: click (>=8.1.2,<9.0.0)
Requires-Dist: lxml (>=4.8.0,<5.0.0)
Requires-Dist: more-itertools (>=8.12.0,<9.0.0)
Requires-Dist: sfdata-stream-parser (==0.4.0)
Requires-Dist: tablib[cli,xlsx] (>=3.2.0,<4.0.0)
Requires-Dist: xmlschema (>=1.10.0,<2.0.0)
